{
  "buildFiles": [
    "/usr/local/flutter/packages/flutter_tools/gradle/src/main/groovy/CMakeLists.txt"
  ],
  "cleanCommandsComponents": [
    [
      "/usr/local/androidsdk/cmake/3.22.1/bin/ninja",
      "-C",
      "/workspaces/quick-chat/android/app/.cxx/RelWithDebInfo/591d5p6c/x86",
      "clean"
    ]
  ],
  "buildTargetsCommandComponents": [
    "/usr/local/androidsdk/cmake/3.22.1/bin/ninja",
    "-C",
    "/workspaces/quick-chat/android/app/.cxx/RelWithDebInfo/591d5p6c/x86",
    "{LIST_OF_TARGETS_TO_BUILD}"
  ],
  "libraries": {},
  "toolchains": {
    "toolchain": {
      "cCompilerExecutable": "/usr/local/androidsdk/ndk/26.3.11579264/toolchains/llvm/prebuilt/linux-x86_64/bin/clang.lld",
      "cppCompilerExecutable": "/usr/local/androidsdk/ndk/26.3.11579264/toolchains/llvm/prebuilt/linux-x86_64/bin/clang++.lld"
    }
  },
  "cFileExtensions": [],
  "cppFileExtensions": []
}